flex/data/__init__.py
flex/data/_version.py
flex/data/datalake.py
flex/data/py.typed
flex/data/trading_db.py
flex/data/warehouse.py
flex_data_sdk-1.0.0.dist-info/licenses/LICENSE
flex_data_sdk-1.0.0.dist-info/WHEEL
flex_data_sdk-1.0.0.dist-info/METADATA
flex_data_sdk-1.0.0.dist-info/RECORD
