Metadata-Version: 2.4
Name: flex-data-sdk
Version: 1.0.0
Summary: Handy tools for data access
Requires-Python: >= 3.9
License-File: LICENSE
Requires-Dist: pandas>=2
Requires-Dist: adlfs>=2023
Requires-Dist: fsspec>=2023
Requires-Dist: pyarrow>=14
Requires-Dist: sqlalchemy>=2
Requires-Dist: pyodbc>=4
Requires-Dist: azure-identity>=1
Requires-Dist: psycopg2-binary>=2
